priwo/__init__.py
priwo/_version.py
priwo/presto/__init__.py
priwo/presto/bpf.py
priwo/presto/dat.py
priwo/presto/fft.py
priwo/presto/inf.py
priwo/presto/pfd.py
priwo/sigproc/__init__.py
priwo/sigproc/fil.py
priwo/sigproc/hdr.py
priwo/sigproc/tim.py
priwo/timing/__init__.py
priwo/timing/polycos.py
priwo-0.0.3.dist-info/LICENSE
priwo-0.0.3.dist-info/METADATA
priwo-0.0.3.dist-info/WHEEL
priwo-0.0.3.dist-info/top_level.txt
priwo-0.0.3.dist-info/RECORD
