Metadata-Version: 2.1
Name: priwo
Version: 0.0.3
Summary: "I/O for common pulsar data formats."
Author: "Ujjwal Panda"
Author-email: "ujjwalpanda97@gmail.com"
License: MIT License
Project-URL: Home Page, https://github.com/astrogewgaw/priwo
Project-URL: Source Code, https://github.com/astrogewgaw/priwo
Project-URL: Documentation, https://priwo.readthedocs.io/en/latest
Project-URL: Bug Reports, https://github.com/astrogewgaw/priwo/issues
Classifier: Operating System :: Unix
Classifier: Operating System :: MacOS :: MacOS X
Classifier: Operating System :: Microsoft :: Windows
Classifier: Programming Language :: Python :: 3.6
Classifier: Programming Language :: Python :: 3.7
Classifier: Programming Language :: Python :: 3.8
Classifier: Programming Language :: Python :: 3.9
Classifier: Programming Language :: Python :: 3.10
Classifier: Programming Language :: Python :: 3.11
Classifier: License :: OSI Approved :: MIT License
Classifier: Topic :: Scientific/Engineering :: Astronomy
Requires-Python: >=3.6
License-File: LICENSE
Requires-Dist: pabo (>=0.1.3)
